fastpass-0.0.6.dist-info/METADATA
fastpass-0.0.6.dist-info/WHEEL
fastpass-0.0.6.dist-info/entry_points.txt
fastpass/__about__.py
fastpass/__init__.py
fastpass/__main__.py
fastpass/cli/__init__.py
fastpass/cli/app.py
fastpass/core/__init__.py
fastpass/core/passworder.py
fastpass-0.0.6.dist-info/RECORD
